pyautodata/__init__.py
pyautodata/alias.py
pyautodata/attributes.py
pyautodata/autodata.py
pyautodata/base.py
pyautodata/builtins.py
pyautodata/dataframe.py
pyautodata/dates.py
pyautodata/fakes.py
pyautodata/generator.py
pyautodata-0.1.6.dist-info/LICENSE
pyautodata-0.1.6.dist-info/METADATA
pyautodata-0.1.6.dist-info/WHEEL
pyautodata-0.1.6.dist-info/entry_points.txt
pyautodata-0.1.6.dist-info/top_level.txt
pyautodata-0.1.6.dist-info/RECORD
