Metadata-Version: 2.1
Name: pyautodata
Version: 0.1.6
Summary: Python library designed to minimize the setup/arrange phase of your unit tests
Home-page: https://github.com/christianhelle/pyautodata
Author: Christian Helle
Author-email: christian.helle@outlook.com
License: MIT License
Platform: UNKNOWN
Requires-Python: >=3.7
Requires-Dist: pandas
Requires-Dist: pyspark
Requires-Dist: faker
